concertina/__init__.py
concertina/__main__.py
concertina/base_models.py
concertina/chords.py
concertina/cli.py
concertina/layouts.py
concertina/pitches.py
concertina/scales.py
concertina-0.0.1.dist-info/WHEEL
concertina-0.0.1.dist-info/METADATA
concertina-0.0.1.dist-info/RECORD
