Metadata-Version: 2.1
Name: concertina
Version: 0.0.1
Summary: 
Author: Ryan J. Miller
Author-email: rjmiller10@gmail.com
Requires-Python: >=3.10,<4.0
Classifier: Programming Language :: Python :: 3
Classifier: Programming Language :: Python :: 3.10
Classifier: Programming Language :: Python :: 3.11
Requires-Dist: musthe (>=1.0.0,<2.0.0)
Requires-Dist: pydantic (>=1.10.2,<2.0.0)
Requires-Dist: rich (>=12.6.0,<13.0.0)
